setup.py
django_kiss.egg-info/PKG-INFO
django_kiss.egg-info/SOURCES.txt
django_kiss.egg-info/dependency_links.txt
django_kiss.egg-info/requires.txt
django_kiss.egg-info/top_level.txt
kiss/__init__.py
kiss/api.py
kiss/context_processors.py
kiss/middleware.py
kiss/models.py
kiss/tasks.py
kiss/storage/__init__.py
kiss/storage/base.py
kiss/storage/session.py
kiss/tests/__init__.py
kiss/tests/test_settings.py
kiss/tests/tests.py