Metadata-Version: 1.0
Name: django-kiss
Version: 0.1
Summary: A Django application for integrating KISSmetrics customer analytics
Home-page: http://github.com/johnboxall/django_kiss
Author: John Boxall
Author-email: john@mobify.com
License: Copyright (c) 2012 Mobify, http://www.mobify.com/
